{
  "version": 1,
  "schema": {
    "target_areas": [
      "abs",
      "calves",
      "fullBody",
      "glutes",
      "hamstrings",
      "hipFlexors",
      "lowerBack",
      "obliques",
      "quads",
      "upperBody"
    ],
    "type": [
      "balance",
      "cardio",
      "core",
      "mobility",
      "strength"
    ],
    "impact": [
      "high",
      "low",
      "med"
    ],
    "symmetry": [
      "alternating",
      "bilateral",
      "unilateral"
    ],
    "pace": [
      "hold",
      "rep"
    ],
    "difficulty_scale": [
      1,
      5
    ]
  },
  "exercises": [
    {
      "id": "plank_saw",
      "name": "Plank Saw",
      "lottie_id": 12236021,
      "lottie_url": "https://iconscout.com/lottie-animation/woman-doing-body-saw-exercise-for-for-shoulders-animation_12236021",
      "target_areas": [
        "abs",
        "upperBody"
      ],
      "type": "core",
      "impact": "low",
      "difficulty": 3,
      "met": 4.5,
      "symmetry": "bilateral",
      "default_side": null,
      "default_duration_sec": 30,
      "rest_after_sec": 15,
      "note": "",
      "pace": "rep",
      "position": "plank",
      "lottie_file": "woman-doing-body-saw-exercise-for-for-shoulders"
    },
    {
      "id": "alternating_superman",
      "name": "Alternating Superman",
      "lottie_id": 12236051,
      "lottie_url": "https://iconscout.com/lottie-animation/woman-doing-alternating-superman-exercise-for-back-animation_12236051",
      "target_areas": [
        "lowerBack"
      ],
      "type": "strength",
      "impact": "low",
      "difficulty": 2,
      "met": 3.5,
      "symmetry": "alternating",
      "default_side": null,
      "default_duration_sec": 30,
      "rest_after_sec": 15,
      "note": "",
      "pace": "rep",
      "position": "prone",
      "lottie_file": "woman-doing-alternating-superman-exercise-for-back"
    },
    {
      "id": "bird_dog",
      "name": "Bird Dog",
      "lottie_id": 12236050,
      "lottie_url": "https://iconscout.com/lottie-animation/woman-doing-bird-dog-exercise-for-back-animation_12236050",
      "target_areas": [
        "lowerBack",
        "abs"
      ],
      "type": "balance",
      "impact": "low",
      "difficulty": 2,
      "met": 3.5,
      "symmetry": "alternating",
      "default_side": null,
      "default_duration_sec": 30,
      "rest_after_sec": 15,
      "note": "",
      "pace": "rep",
      "position": "quadruped",
      "lottie_file": "woman-doing-bird-dog-exercise-for-back"
    },
    {
      "id": "floor_dip",
      "name": "Floor Dip",
      "lottie_id": 12236008,
      "lottie_url": "https://iconscout.com/lottie-animation/woman-doing-floor-dip-exercise-for-arm-animation_12236008",
      "target_areas": [
        "upperBody"
      ],
      "type": "strength",
      "impact": "low",
      "difficulty": 3,
      "met": 5.0,
      "symmetry": "bilateral",
      "default_side": null,
      "default_duration_sec": 30,
      "rest_after_sec": 15,
      "note": "",
      "pace": "rep",
      "position": "seated",
      "lottie_file": "woman-doing-floor-dip-exercise-for-arm"
    },
    {
      "id": "jumping_lunges",
      "name": "Jumping Lunges",
      "lottie_id": 12236015,
      "lottie_url": "https://iconscout.com/lottie-animation/woman-doing-jumping-lunges-cardio-exercise-animation_12236015",
      "target_areas": [
        "quads",
        "glutes"
      ],
      "type": "cardio",
      "impact": "high",
      "difficulty": 4,
      "met": 9.0,
      "symmetry": "alternating",
      "default_side": null,
      "default_duration_sec": 30,
      "rest_after_sec": 15,
      "note": "",
      "pace": "rep",
      "position": "standing",
      "lottie_file": "woman-doing-jumping-lunges-cardio-exercise"
    },
    {
      "id": "kneeling_shoulder_tap",
      "name": "Kneeling Shoulder Tap",
      "lottie_id": 12236025,
      "lottie_url": "https://iconscout.com/lottie-animation/woman-doing-kneeling-shoulder-tap-exercise-for-chest-animation_12236025",
      "target_areas": [
        "abs",
        "upperBody"
      ],
      "type": "core",
      "impact": "low",
      "difficulty": 2,
      "met": 4.5,
      "symmetry": "alternating",
      "default_side": null,
      "default_duration_sec": 30,
      "rest_after_sec": 15,
      "note": "",
      "pace": "rep",
      "position": "quadruped",
      "lottie_file": "woman-doing-kneeling-shoulder-tap-exercise-for-chest"
    },
    {
      "id": "mountain_climbers",
      "name": "Mountain Climbers",
      "lottie_id": 12236048,
      "lottie_url": "https://iconscout.com/lottie-animation/woman-doing-mountain-climber-exercise-for-abs-animation_12236048",
      "target_areas": [
        "abs",
        "fullBody"
      ],
      "type": "cardio",
      "impact": "high",
      "difficulty": 3,
      "met": 8.0,
      "symmetry": "alternating",
      "default_side": null,
      "default_duration_sec": 30,
      "rest_after_sec": 15,
      "note": "",
      "pace": "rep",
      "position": "plank",
      "lottie_file": "woman-doing-mountain-climber-exercise-for-abs"
    },
    {
      "id": "back_extension_lying",
      "name": "Back Extension",
      "lottie_id": 12236049,
      "lottie_url": "https://iconscout.com/lottie-animation/woman-doing-lying-back-extension-exercise-for-back-animation_12236049",
      "target_areas": [
        "lowerBack"
      ],
      "type": "strength",
      "impact": "low",
      "difficulty": 2,
      "met": 3.5,
      "symmetry": "bilateral",
      "default_side": null,
      "default_duration_sec": 30,
      "rest_after_sec": 15,
      "note": "",
      "pace": "rep",
      "position": "prone",
      "lottie_file": "woman-doing-lying-back-extension-exercise-for-back"
    },
    {
      "id": "superman_pull_up",
      "name": "Superman Pull-Up",
      "lottie_id": 12236054,
      "lottie_url": "https://iconscout.com/lottie-animation/woman-doing-superman-pull-up-exercise-for-back-animation_12236054",
      "target_areas": [
        "lowerBack",
        "upperBody"
      ],
      "type": "strength",
      "impact": "low",
      "difficulty": 2,
      "met": 4.0,
      "symmetry": "bilateral",
      "default_side": null,
      "default_duration_sec": 30,
      "rest_after_sec": 15,
      "note": "",
      "pace": "rep",
      "position": "prone",
      "lottie_file": "woman-doing-superman-pull-up-exercise-for-back"
    },
    {
      "id": "superman_hold",
      "name": "Superman Hold",
      "lottie_id": 12236055,
      "lottie_url": "https://iconscout.com/lottie-animation/woman-doing-superman-exercise-for-back-animation_12236055",
      "target_areas": [
        "lowerBack"
      ],
      "type": "core",
      "impact": "low",
      "difficulty": 2,
      "met": 3.5,
      "symmetry": "bilateral",
      "default_side": null,
      "default_duration_sec": 30,
      "rest_after_sec": 15,
      "note": "",
      "pace": "hold",
      "position": "prone",
      "lottie_file": "woman-doing-superman-exercise-for-back"
    },
    {
      "id": "w_raise",
      "name": "W Raise",
      "lottie_id": 12236053,
      "lottie_url": "https://iconscout.com/lottie-animation/woman-doing-w-back-extension-exercise-for-back-animation_12236053",
      "target_areas": [
        "lowerBack",
        "upperBody"
      ],
      "type": "strength",
      "impact": "low",
      "difficulty": 2,
      "met": 3.5,
      "symmetry": "bilateral",
      "default_side": null,
      "default_duration_sec": 30,
      "rest_after_sec": 15,
      "note": "",
      "pace": "rep",
      "position": "prone",
      "lottie_file": "woman-doing-w-back-extension-exercise-for-back"
    },
    {
      "id": "y_raise",
      "name": "Y Raise",
      "lottie_id": 12236052,
      "lottie_url": "https://iconscout.com/lottie-animation/woman-doing-y-back-extension-exercise-for-back-animation_12236052",
      "target_areas": [
        "lowerBack",
        "upperBody"
      ],
      "type": "strength",
      "impact": "low",
      "difficulty": 2,
      "met": 3.5,
      "symmetry": "bilateral",
      "default_side": null,
      "default_duration_sec": 30,
      "rest_after_sec": 15,
      "note": "",
      "pace": "rep",
      "position": "prone",
      "lottie_file": "woman-doing-y-back-extension-exercise-for-back"
    },
    {
      "id": "bent_knee_hip_raise",
      "name": "Bent Knee Hip Raise",
      "lottie_id": 12193330,
      "lottie_url": "https://iconscout.com/lottie-animation/woman-doing-bent-knee-hip-raise-exercise-for-abs-animation_12193330",
      "target_areas": [
        "abs"
      ],
      "type": "core",
      "impact": "low",
      "difficulty": 2,
      "met": 4.5,
      "symmetry": "bilateral",
      "default_side": null,
      "default_duration_sec": 30,
      "rest_after_sec": 15,
      "note": "",
      "pace": "rep",
      "position": "supine",
      "lottie_file": "woman-doing-bent-knee-hip-raise-exercise-for-abs"
    },
    {
      "id": "boat_flutters",
      "name": "Boat Hold + Flutter",
      "lottie_id": 12193339,
      "lottie_url": "https://iconscout.com/lottie-animation/woman-doing-boat-hold-leg-flutters-exercise-for-abs-animation_12193339",
      "target_areas": [
        "abs"
      ],
      "type": "core",
      "impact": "low",
      "difficulty": 4,
      "met": 5.5,
      "symmetry": "bilateral",
      "default_side": null,
      "default_duration_sec": 30,
      "rest_after_sec": 15,
      "note": "",
      "pace": "rep",
      "position": "seated",
      "lottie_file": "woman-doing-boat-hold-leg-flutters-exercise-for-abs"
    },
    {
      "id": "boat_bicycle",
      "name": "Boat Hold Bicycle",
      "lottie_id": 12193331,
      "lottie_url": "https://iconscout.com/lottie-animation/woman-doing-boat-hold-bicycle-exercise-for-abs-animation_12193331",
      "target_areas": [
        "abs",
        "obliques"
      ],
      "type": "core",
      "impact": "low",
      "difficulty": 4,
      "met": 5.5,
      "symmetry": "alternating",
      "default_side": null,
      "default_duration_sec": 30,
      "rest_after_sec": 15,
      "note": "",
      "pace": "rep",
      "position": "seated",
      "lottie_file": "woman-doing-boat-hold-bicycle-exercise-for-abs"
    },
    {
      "id": "cocoon_crunch",
      "name": "Cocoon Crunch",
      "lottie_id": 12193332,
      "lottie_url": "https://iconscout.com/lottie-animation/woman-doing-cocoons-exercise-for-abs-animation_12193332",
      "target_areas": [
        "abs"
      ],
      "type": "core",
      "impact": "low",
      "difficulty": 3,
      "met": 5.0,
      "symmetry": "bilateral",
      "default_side": null,
      "default_duration_sec": 30,
      "rest_after_sec": 15,
      "note": "",
      "pace": "rep",
      "position": "supine",
      "lottie_file": "woman-doing-cocoons-exercise-for-abs"
    },
    {
      "id": "crunch_knee_raise",
      "name": "Crunch + Knee Raise",
      "lottie_id": 12193334,
      "lottie_url": "https://iconscout.com/lottie-animation/woman-doing-crunch-knee-raise-exercise-for-abs-animation_12193334",
      "target_areas": [
        "abs"
      ],
      "type": "core",
      "impact": "low",
      "difficulty": 2,
      "met": 4.5,
      "symmetry": "bilateral",
      "default_side": null,
      "default_duration_sec": 30,
      "rest_after_sec": 15,
      "note": "",
      "pace": "rep",
      "position": "supine",
      "lottie_file": "woman-doing-crunch-knee-raise-exercise-for-abs"
    },
    {
      "id": "alt_knee_raise_crunch",
      "name": "Alternating Knee Raise Crunch",
      "lottie_id": 12193306,
      "lottie_url": "https://iconscout.com/lottie-animation/woman-doing-crunch-hold-knee-raise-alternating-exercise-for-abs-animation_12193306",
      "target_areas": [
        "abs"
      ],
      "type": "core",
      "impact": "low",
      "difficulty": 3,
      "met": 5.0,
      "symmetry": "alternating",
      "default_side": null,
      "default_duration_sec": 30,
      "rest_after_sec": 15,
      "note": "",
      "pace": "rep",
      "position": "supine",
      "lottie_file": "woman-doing-crunch-hold-knee-raise-alternating-exercise-for-abs"
    },
    {
      "id": "crunch",
      "name": "Crunch",
      "lottie_id": 12193333,
      "lottie_url": "https://iconscout.com/lottie-animation/woman-doing-crunch-exercise-for-abs-animation_12193333",
      "target_areas": [
        "abs"
      ],
      "type": "core",
      "impact": "low",
      "difficulty": 1,
      "met": 4.0,
      "symmetry": "bilateral",
      "default_side": null,
      "default_duration_sec": 30,
      "rest_after_sec": 15,
      "note": "",
      "pace": "rep",
      "position": "supine",
      "lottie_file": "woman-doing-crunch-exercise-for-abs"
    },
    {
      "id": "dead_bug",
      "name": "Dead Bug",
      "lottie_id": 12193326,
      "lottie_url": "https://iconscout.com/lottie-animation/woman-doing-dead-bug-exercise-for-abs-animation_12193326",
      "target_areas": [
        "abs"
      ],
      "type": "core",
      "impact": "low",
      "difficulty": 2,
      "met": 4.0,
      "symmetry": "alternating",
      "default_side": null,
      "default_duration_sec": 30,
      "rest_after_sec": 15,
      "note": "",
      "pace": "rep",
      "position": "supine",
      "lottie_file": "woman-doing-dead-bug-exercise-for-abs"
    },
    {
      "id": "dead_bug_leg_lower",
      "name": "Dead Bug Leg Lower",
      "lottie_id": 12193327,
      "lottie_url": "https://iconscout.com/lottie-animation/woman-doing-dead-bug-leg-lowering-exercise-for-abs-animation_12193327",
      "target_areas": [
        "abs"
      ],
      "type": "core",
      "impact": "low",
      "difficulty": 3,
      "met": 4.5,
      "symmetry": "alternating",
      "default_side": null,
      "default_duration_sec": 30,
      "rest_after_sec": 15,
      "note": "",
      "pace": "rep",
      "position": "supine",
      "lottie_file": "woman-doing-dead-bug-leg-lowering-exercise-for-abs"
    },
    {
      "id": "diagonal_plank",
      "name": "Diagonal Plank",
      "lottie_id": 12193319,
      "lottie_url": "https://iconscout.com/lottie-animation/woman-doing-diagonal-plank-exercise-for-abs-animation_12193319",
      "target_areas": [
        "abs",
        "obliques"
      ],
      "type": "core",
      "impact": "low",
      "difficulty": 3,
      "met": 5.0,
      "symmetry": "bilateral",
      "default_side": null,
      "default_duration_sec": 30,
      "rest_after_sec": 15,
      "note": "",
      "pace": "hold",
      "position": "plank",
      "lottie_file": "woman-doing-diagonal-plank-exercise-for-abs"
    },
    {
      "id": "flutter_kicks",
      "name": "Flutter Kicks",
      "lottie_id": 12193338,
      "lottie_url": "https://iconscout.com/lottie-animation/woman-doing-flutter-kicks-exercise-for-abs-animation_12193338",
      "target_areas": [
        "abs"
      ],
      "type": "core",
      "impact": "low",
      "difficulty": 2,
      "met": 4.5,
      "symmetry": "alternating",
      "default_side": null,
      "default_duration_sec": 30,
      "rest_after_sec": 15,
      "note": "",
      "pace": "rep",
      "position": "supine",
      "lottie_file": "woman-doing-flutter-kicks-exercise-for-abs"
    },
    {
      "id": "glute_bridge_march",
      "name": "Glute Bridge March",
      "lottie_id": 12193349,
      "lottie_url": "https://iconscout.com/lottie-animation/woman-doing-glute-bridge-march-exercise-for-legs-and-core-animation_12193349",
      "target_areas": [
        "glutes",
        "abs"
      ],
      "type": "core",
      "impact": "low",
      "difficulty": 2,
      "met": 4.5,
      "symmetry": "alternating",
      "default_side": null,
      "default_duration_sec": 30,
      "rest_after_sec": 15,
      "note": "",
      "pace": "rep",
      "position": "supine",
      "lottie_file": "woman-doing-glute-bridge-march-exercise-for-legs-and-core"
    },
    {
      "id": "bicycle_crunch",
      "name": "Bicycle Crunch",
      "lottie_id": 12193328,
      "lottie_url": "https://iconscout.com/lottie-animation/woman-doing-lying-bicycle-exercise-for-abs-animation_12193328",
      "target_areas": [
        "abs",
        "obliques"
      ],
      "type": "core",
      "impact": "low",
      "difficulty": 2,
      "met": 5.0,
      "symmetry": "alternating",
      "default_side": null,
      "default_duration_sec": 30,
      "rest_after_sec": 15,
      "note": "",
      "pace": "rep",
      "position": "supine",
      "lottie_file": "woman-doing-lying-bicycle-exercise-for-abs"
    },
    {
      "id": "alt_leg_raise",
      "name": "Alternating Leg Raise",
      "lottie_id": 12193336,
      "lottie_url": "https://iconscout.com/lottie-animation/woman-doing-lying-leg-raise-alternating-exercise-for-abs-animation_12193336",
      "target_areas": [
        "abs"
      ],
      "type": "core",
      "impact": "low",
      "difficulty": 2,
      "met": 4.5,
      "symmetry": "alternating",
      "default_side": null,
      "default_duration_sec": 30,
      "rest_after_sec": 15,
      "note": "",
      "pace": "rep",
      "position": "supine",
      "lottie_file": "woman-doing-lying-leg-raise-alternating-exercise-for-abs"
    },
    {
      "id": "leg_raise_hold",
      "name": "Leg Raise + Hold",
      "lottie_id": 12193337,
      "lottie_url": "https://iconscout.com/lottie-animation/woman-doing-lying-leg-raise-and-hold-exercise-for-abs-animation_12193337",
      "target_areas": [
        "abs"
      ],
      "type": "core",
      "impact": "low",
      "difficulty": 3,
      "met": 5.0,
      "symmetry": "bilateral",
      "default_side": null,
      "default_duration_sec": 30,
      "rest_after_sec": 15,
      "note": "",
      "pace": "hold",
      "position": "supine",
      "lottie_file": "woman-doing-lying-leg-raise-and-hold-exercise-for-abs"
    },
    {
      "id": "leg_raise",
      "name": "Leg Raise",
      "lottie_id": 12193344,
      "lottie_url": "https://iconscout.com/lottie-animation/woman-doing-lying-leg-raise-exercise-for-abs-animation_12193344",
      "target_areas": [
        "abs"
      ],
      "type": "core",
      "impact": "low",
      "difficulty": 2,
      "met": 4.5,
      "symmetry": "bilateral",
      "default_side": null,
      "default_duration_sec": 30,
      "rest_after_sec": 15,
      "note": "",
      "pace": "rep",
      "position": "supine",
      "lottie_file": "woman-doing-lying-leg-raise-exercise-for-abs"
    },
    {
      "id": "leg_raise_hip_lift",
      "name": "Leg Raise + Hip Lift",
      "lottie_id": 12193348,
      "lottie_url": "https://iconscout.com/lottie-animation/woman-doing-lying-leg-raise-with-hip-lift-exercise-for-abs-animation_12193348",
      "target_areas": [
        "abs"
      ],
      "type": "core",
      "impact": "low",
      "difficulty": 4,
      "met": 5.5,
      "symmetry": "bilateral",
      "default_side": null,
      "default_duration_sec": 30,
      "rest_after_sec": 15,
      "note": "",
      "pace": "rep",
      "position": "supine",
      "lottie_file": "woman-doing-lying-leg-raise-with-hip-lift-exercise-for-abs"
    },
    {
      "id": "reverse_crunch",
      "name": "Reverse Crunch",
      "lottie_id": 12193342,
      "lottie_url": "https://iconscout.com/lottie-animation/woman-doing-reverse-crunch-exercise-for-abs-animation_12193342",
      "target_areas": [
        "abs"
      ],
      "type": "core",
      "impact": "low",
      "difficulty": 2,
      "met": 4.5,
      "symmetry": "bilateral",
      "default_side": null,
      "default_duration_sec": 30,
      "rest_after_sec": 15,
      "note": "",
      "pace": "rep",
      "position": "supine",
      "lottie_file": "woman-doing-reverse-crunch-exercise-for-abs"
    },
    {
      "id": "seated_knee_tuck",
      "name": "Seated Knee Tuck",
      "lottie_id": 12193311,
      "lottie_url": "https://iconscout.com/lottie-animation/woman-doing-seated-knee-tuck-exercise-for-abs-animation_12193311",
      "target_areas": [
        "abs"
      ],
      "type": "core",
      "impact": "low",
      "difficulty": 2,
      "met": 4.5,
      "symmetry": "bilateral",
      "default_side": null,
      "default_duration_sec": 30,
      "rest_after_sec": 15,
      "note": "",
      "pace": "rep",
      "position": "seated",
      "lottie_file": "woman-doing-seated-knee-tuck-exercise-for-abs"
    },
    {
      "id": "side_plank",
      "name": "Side Plank",
      "lottie_id": 12193318,
      "lottie_url": "https://iconscout.com/lottie-animation/woman-doing-side-bridge-exercise-for-abs-animation_12193318",
      "target_areas": [
        "obliques"
      ],
      "type": "core",
      "impact": "low",
      "difficulty": 3,
      "met": 4.0,
      "symmetry": "unilateral",
      "default_side": "right",
      "default_duration_sec": 30,
      "rest_after_sec": 15,
      "note": "Mirror animation horizontally to render the left side.",
      "pace": "hold",
      "position": "sideLying",
      "lottie_file": "woman-doing-side-bridge-exercise-for-abs"
    },
    {
      "id": "side_crunch",
      "name": "Side Crunch",
      "lottie_id": 12193317,
      "lottie_url": "https://iconscout.com/lottie-animation/woman-doing-side-crunches-exercise-for-abs-animation_12193317",
      "target_areas": [
        "obliques"
      ],
      "type": "core",
      "impact": "low",
      "difficulty": 2,
      "met": 4.5,
      "symmetry": "unilateral",
      "default_side": "right",
      "default_duration_sec": 30,
      "rest_after_sec": 15,
      "note": "Mirror animation horizontally to render the left side.",
      "pace": "rep",
      "position": "sideLying",
      "lottie_file": "woman-doing-side-crunches-exercise-for-abs"
    },
    {
      "id": "side_crunch_hip_raise",
      "name": "Side Crunch + Hip Raise",
      "lottie_id": 12193316,
      "lottie_url": "https://iconscout.com/lottie-animation/woman-doing-side-crunches-hip-raise-exercise-for-abs-animation_12193316",
      "target_areas": [
        "obliques"
      ],
      "type": "core",
      "impact": "low",
      "difficulty": 3,
      "met": 5.0,
      "symmetry": "unilateral",
      "default_side": "right",
      "default_duration_sec": 30,
      "rest_after_sec": 15,
      "note": "Mirror animation horizontally to render the left side.",
      "pace": "rep",
      "position": "sideLying",
      "lottie_file": "woman-doing-side-crunches-hip-raise-exercise-for-abs"
    },
    {
      "id": "sit_up",
      "name": "Sit-Up",
      "lottie_id": 12193315,
      "lottie_url": "https://iconscout.com/lottie-animation/woman-doing-sit-up-exercise-for-abs-animation_12193315",
      "target_areas": [
        "abs"
      ],
      "type": "core",
      "impact": "low",
      "difficulty": 2,
      "met": 5.0,
      "symmetry": "bilateral",
      "default_side": null,
      "default_duration_sec": 30,
      "rest_after_sec": 15,
      "note": "",
      "pace": "rep",
      "position": "supine",
      "lottie_file": "woman-doing-sit-up-exercise-for-abs"
    },
    {
      "id": "standing_hip_abduction",
      "name": "Standing Hip Abduction",
      "lottie_id": 12193347,
      "lottie_url": "https://iconscout.com/lottie-animation/woman-doing-standing-hip-abduction-exercise-for-legs-animation_12193347",
      "target_areas": [
        "glutes"
      ],
      "type": "strength",
      "impact": "low",
      "difficulty": 2,
      "met": 4.0,
      "symmetry": "alternating",
      "default_side": null,
      "default_duration_sec": 30,
      "rest_after_sec": 15,
      "note": "",
      "pace": "rep",
      "position": "standing",
      "lottie_file": "woman-doing-standing-hip-abduction-exercise-for-legs"
    },
    {
      "id": "standing_side_bend",
      "name": "Standing Side Bend",
      "lottie_id": 12193324,
      "lottie_url": "https://iconscout.com/lottie-animation/woman-doing-standing-side-bend-exercise-for-abs-animation_12193324",
      "target_areas": [
        "obliques"
      ],
      "type": "mobility",
      "impact": "low",
      "difficulty": 1,
      "met": 3.0,
      "symmetry": "unilateral",
      "default_side": "right",
      "default_duration_sec": 30,
      "rest_after_sec": 15,
      "note": "Mirror animation horizontally to render the left side.",
      "pace": "rep",
      "position": "standing",
      "lottie_file": "woman-doing-standing-side-bend-exercise-for-abs"
    },
    {
      "id": "tabletop_bridge",
      "name": "Tabletop Bridge",
      "lottie_id": 12193353,
      "lottie_url": "https://iconscout.com/lottie-animation/woman-doing-tabletop-bridge-exercise-for-legs-animation_12193353",
      "target_areas": [
        "glutes",
        "abs"
      ],
      "type": "strength",
      "impact": "low",
      "difficulty": 2,
      "met": 4.0,
      "symmetry": "bilateral",
      "default_side": null,
      "default_duration_sec": 30,
      "rest_after_sec": 15,
      "note": "",
      "pace": "rep",
      "position": "supine",
      "lottie_file": "woman-doing-tabletop-bridge-exercise-for-legs"
    },
    {
      "id": "tabletop_bridge_knee_lift",
      "name": "Tabletop Bridge + Knee Lift",
      "lottie_id": 12193352,
      "lottie_url": "https://iconscout.com/lottie-animation/woman-doing-tabletop-bridge-with-bent-knee-lift-exercise-for-legs-animation_12193352",
      "target_areas": [
        "glutes",
        "abs"
      ],
      "type": "strength",
      "impact": "low",
      "difficulty": 3,
      "met": 4.5,
      "symmetry": "alternating",
      "default_side": null,
      "default_duration_sec": 30,
      "rest_after_sec": 15,
      "note": "",
      "pace": "rep",
      "position": "supine",
      "lottie_file": "woman-doing-tabletop-bridge-with-bent-knee-lift-exercise-for-legs"
    },
    {
      "id": "tabletop_hold_knee_lift",
      "name": "Tabletop Hold + Knee Lift",
      "lottie_id": 12193351,
      "lottie_url": "https://iconscout.com/lottie-animation/woman-doing-tabletop-hold-with-bent-knee-lift-exercise-for-legs-animation_12193351",
      "target_areas": [
        "glutes",
        "abs"
      ],
      "type": "balance",
      "impact": "low",
      "difficulty": 3,
      "met": 4.5,
      "symmetry": "alternating",
      "default_side": null,
      "default_duration_sec": 30,
      "rest_after_sec": 15,
      "note": "",
      "pace": "hold",
      "position": "quadruped",
      "lottie_file": "woman-doing-tabletop-hold-with-bent-knee-lift-exercise-for-legs"
    },
    {
      "id": "v_up",
      "name": "V-Up",
      "lottie_id": 12193322,
      "lottie_url": "https://iconscout.com/lottie-animation/woman-doing-v-up-exercise-for-abs-animation_12193322",
      "target_areas": [
        "abs"
      ],
      "type": "core",
      "impact": "low",
      "difficulty": 4,
      "met": 5.5,
      "symmetry": "bilateral",
      "default_side": null,
      "default_duration_sec": 30,
      "rest_after_sec": 15,
      "note": "",
      "pace": "rep",
      "position": "supine",
      "lottie_file": "woman-doing-v-up-exercise-for-abs"
    },
    {
      "id": "vertical_leg_crunch",
      "name": "Vertical Leg Crunch",
      "lottie_id": 12193321,
      "lottie_url": "https://iconscout.com/lottie-animation/woman-doing-vertical-leg-crunch-exercise-for-abs-animation_12193321",
      "target_areas": [
        "abs"
      ],
      "type": "core",
      "impact": "low",
      "difficulty": 3,
      "met": 5.0,
      "symmetry": "bilateral",
      "default_side": null,
      "default_duration_sec": 30,
      "rest_after_sec": 15,
      "note": "",
      "pace": "rep",
      "position": "supine",
      "lottie_file": "woman-doing-vertical-leg-crunch-exercise-for-abs"
    },
    {
      "id": "windshield_wipers",
      "name": "Windshield Wipers",
      "lottie_id": 12193329,
      "lottie_url": "https://iconscout.com/lottie-animation/woman-doing-wipers-exercise-for-abs-animation_12193329",
      "target_areas": [
        "abs",
        "obliques"
      ],
      "type": "core",
      "impact": "low",
      "difficulty": 4,
      "met": 5.5,
      "symmetry": "alternating",
      "default_side": null,
      "default_duration_sec": 30,
      "rest_after_sec": 15,
      "note": "",
      "pace": "rep",
      "position": "supine",
      "lottie_file": "woman-doing-wipers-exercise-for-abs"
    },
    {
      "id": "reverse_to_forward_lunge",
      "name": "Reverse-to-Forward Lunge",
      "lottie_id": 12193231,
      "lottie_url": "https://iconscout.com/lottie-animation/woman-doing-back-to-forward-lunge-exercise-for-legs-animation_12193231",
      "target_areas": [
        "quads",
        "glutes"
      ],
      "type": "strength",
      "impact": "low",
      "difficulty": 3,
      "met": 6.0,
      "symmetry": "unilateral",
      "default_side": "right",
      "default_duration_sec": 30,
      "rest_after_sec": 15,
      "note": "Mirror animation horizontally to render the left side.",
      "pace": "rep",
      "position": "standing",
      "lottie_file": "woman-doing-back-to-forward-lunge-exercise-for-legs"
    },
    {
      "id": "air_squat",
      "name": "Air Squat",
      "lottie_id": 12193252,
      "lottie_url": "https://iconscout.com/lottie-animation/woman-doing-air-squat-exercise-for-legs-animation_12193252",
      "target_areas": [
        "quads",
        "glutes"
      ],
      "type": "strength",
      "impact": "low",
      "difficulty": 1,
      "met": 5.0,
      "symmetry": "bilateral",
      "default_side": null,
      "default_duration_sec": 30,
      "rest_after_sec": 15,
      "note": "",
      "pace": "rep",
      "position": "standing",
      "lottie_file": "woman-doing-air-squat-exercise-for-legs"
    },
    {
      "id": "donkey_kick",
      "name": "Donkey Kick",
      "lottie_id": 12193232,
      "lottie_url": "https://iconscout.com/lottie-animation/woman-doing-donkey-kick-exercise-for-legs-animation_12193232",
      "target_areas": [
        "glutes"
      ],
      "type": "strength",
      "impact": "low",
      "difficulty": 1,
      "met": 4.0,
      "symmetry": "unilateral",
      "default_side": "left",
      "default_duration_sec": 30,
      "rest_after_sec": 15,
      "note": "Mirror animation horizontally to render the right side.",
      "pace": "rep",
      "position": "quadruped",
      "lottie_file": "woman-doing-donkey-kick-exercise-for-legs"
    },
    {
      "id": "donkey_kick_pulse",
      "name": "Donkey Kick Pulse",
      "lottie_id": 12193220,
      "lottie_url": "https://iconscout.com/lottie-animation/woman-doing-donkey-kick-pulse-exercise-for-legs-animation_12193220",
      "target_areas": [
        "glutes"
      ],
      "type": "strength",
      "impact": "low",
      "difficulty": 2,
      "met": 4.5,
      "symmetry": "unilateral",
      "default_side": "left",
      "default_duration_sec": 30,
      "rest_after_sec": 15,
      "note": "Mirror animation horizontally to render the right side.",
      "pace": "rep",
      "position": "quadruped",
      "lottie_file": "woman-doing-donkey-kick-pulse-exercise-for-legs"
    },
    {
      "id": "donkey_kickback",
      "name": "Donkey Kickback",
      "lottie_id": 12193233,
      "lottie_url": "https://iconscout.com/lottie-animation/woman-doing-donkey-kickback-exercise-for-legs-animation_12193233",
      "target_areas": [
        "glutes"
      ],
      "type": "strength",
      "impact": "low",
      "difficulty": 2,
      "met": 4.5,
      "symmetry": "unilateral",
      "default_side": "left",
      "default_duration_sec": 30,
      "rest_after_sec": 15,
      "note": "Mirror animation horizontally to render the right side.",
      "pace": "rep",
      "position": "quadruped",
      "lottie_file": "woman-doing-donkey-kickback-exercise-for-legs"
    },
    {
      "id": "fire_hydrant",
      "name": "Fire Hydrant",
      "lottie_id": 12193219,
      "lottie_url": "https://iconscout.com/lottie-animation/woman-doing-fire-hydrant-exercise-for-legs-animation_12193219",
      "target_areas": [
        "glutes"
      ],
      "type": "strength",
      "impact": "low",
      "difficulty": 2,
      "met": 4.5,
      "symmetry": "unilateral",
      "default_side": "left",
      "default_duration_sec": 30,
      "rest_after_sec": 15,
      "note": "Mirror animation horizontally to render the right side.",
      "pace": "rep",
      "position": "quadruped",
      "lottie_file": "woman-doing-fire-hydrant-exercise-for-legs"
    },
    {
      "id": "alt_forward_lunge",
      "name": "Alternating Forward Lunge",
      "lottie_id": 12193234,
      "lottie_url": "https://iconscout.com/lottie-animation/woman-doing-forward-lunges-alternating-exercise-for-legs-animation_12193234",
      "target_areas": [
        "quads",
        "glutes"
      ],
      "type": "strength",
      "impact": "low",
      "difficulty": 2,
      "met": 5.5,
      "symmetry": "alternating",
      "default_side": null,
      "default_duration_sec": 30,
      "rest_after_sec": 15,
      "note": "",
      "pace": "rep",
      "position": "standing",
      "lottie_file": "woman-doing-forward-lunges-alternating-exercise-for-legs"
    },
    {
      "id": "glute_bridge",
      "name": "Glute Bridge",
      "lottie_id": 12193209,
      "lottie_url": "https://iconscout.com/lottie-animation/woman-doing-glute-bridge-exercise-for-legs-animation_12193209",
      "target_areas": [
        "glutes"
      ],
      "type": "strength",
      "impact": "low",
      "difficulty": 1,
      "met": 4.0,
      "symmetry": "bilateral",
      "default_side": null,
      "default_duration_sec": 30,
      "rest_after_sec": 15,
      "note": "",
      "pace": "rep",
      "position": "supine",
      "lottie_file": "woman-doing-glute-bridge-exercise-for-legs"
    },
    {
      "id": "good_morning",
      "name": "Good Morning",
      "lottie_id": 12193218,
      "lottie_url": "https://iconscout.com/lottie-animation/woman-doing-good-morning-exercise-for-legs-animation_12193218",
      "target_areas": [
        "hamstrings",
        "lowerBack"
      ],
      "type": "strength",
      "impact": "low",
      "difficulty": 2,
      "met": 4.0,
      "symmetry": "bilateral",
      "default_side": null,
      "default_duration_sec": 30,
      "rest_after_sec": 15,
      "note": "",
      "pace": "rep",
      "position": "standing",
      "lottie_file": "woman-doing-good-morning-exercise-for-legs"
    },
    {
      "id": "high_plank_leg_raise",
      "name": "High Plank Leg Raise",
      "lottie_id": 12193217,
      "lottie_url": "https://iconscout.com/lottie-animation/woman-doing-high-plank-leg-raise-exercise-for-legs-animation_12193217",
      "target_areas": [
        "glutes",
        "abs"
      ],
      "type": "core",
      "impact": "low",
      "difficulty": 3,
      "met": 5.5,
      "symmetry": "alternating",
      "default_side": null,
      "default_duration_sec": 30,
      "rest_after_sec": 15,
      "note": "",
      "pace": "rep",
      "position": "plank",
      "lottie_file": "woman-doing-high-plank-leg-raise-exercise-for-legs"
    },
    {
      "id": "kneeling_squat",
      "name": "Kneeling Squat",
      "lottie_id": 12193207,
      "lottie_url": "https://iconscout.com/lottie-animation/woman-doing-kneeling-squat-exercise-for-legs-animation_12193207",
      "target_areas": [
        "glutes",
        "quads"
      ],
      "type": "strength",
      "impact": "low",
      "difficulty": 2,
      "met": 4.5,
      "symmetry": "bilateral",
      "default_side": null,
      "default_duration_sec": 30,
      "rest_after_sec": 15,
      "note": "",
      "pace": "rep",
      "position": "quadruped",
      "lottie_file": "woman-doing-kneeling-squat-exercise-for-legs"
    },
    {
      "id": "forward_lunge",
      "name": "Forward Lunge",
      "lottie_id": 12193235,
      "lottie_url": "https://iconscout.com/lottie-animation/woman-doing-left-leg-forward-lunge-exercise-for-legs-animation_12193235",
      "target_areas": [
        "quads",
        "glutes"
      ],
      "type": "strength",
      "impact": "low",
      "difficulty": 2,
      "met": 5.0,
      "symmetry": "unilateral",
      "default_side": "left",
      "default_duration_sec": 30,
      "rest_after_sec": 15,
      "note": "Mirror animation horizontally to render the right side.",
      "pace": "rep",
      "position": "standing",
      "lottie_file": "woman-doing-left-leg-forward-lunge-exercise-for-legs"
    },
    {
      "id": "reverse_lunge",
      "name": "Reverse Lunge",
      "lottie_id": 12193238,
      "lottie_url": "https://iconscout.com/lottie-animation/woman-doing-left-leg-reverse-lunge-exercise-for-legs-animation_12193238",
      "target_areas": [
        "quads",
        "glutes"
      ],
      "type": "strength",
      "impact": "low",
      "difficulty": 2,
      "met": 5.0,
      "symmetry": "unilateral",
      "default_side": "left",
      "default_duration_sec": 30,
      "rest_after_sec": 15,
      "note": "Mirror animation horizontally to render the right side.",
      "pace": "rep",
      "position": "standing",
      "lottie_file": "woman-doing-left-leg-reverse-lunge-exercise-for-legs"
    },
    {
      "id": "low_plank_leg_raise",
      "name": "Low Plank Leg Raise",
      "lottie_id": 12193216,
      "lottie_url": "https://iconscout.com/lottie-animation/woman-doing-low-plank-leg-raise-exercise-for-legs-animation_12193216",
      "target_areas": [
        "glutes",
        "abs"
      ],
      "type": "core",
      "impact": "low",
      "difficulty": 4,
      "met": 5.5,
      "symmetry": "alternating",
      "default_side": null,
      "default_duration_sec": 30,
      "rest_after_sec": 15,
      "note": "",
      "pace": "rep",
      "position": "plank",
      "lottie_file": "woman-doing-low-plank-leg-raise-exercise-for-legs"
    },
    {
      "id": "narrow_squat",
      "name": "Narrow Squat",
      "lottie_id": 12193250,
      "lottie_url": "https://iconscout.com/lottie-animation/woman-doing-narrow-squat-exercise-for-legs-animation_12193250",
      "target_areas": [
        "quads"
      ],
      "type": "strength",
      "impact": "low",
      "difficulty": 2,
      "met": 5.0,
      "symmetry": "bilateral",
      "default_side": null,
      "default_duration_sec": 30,
      "rest_after_sec": 15,
      "note": "",
      "pace": "rep",
      "position": "standing",
      "lottie_file": "woman-doing-narrow-squat-exercise-for-legs"
    },
    {
      "id": "overhead_forward_lunge",
      "name": "Overhead Forward Lunge",
      "lottie_id": 12193227,
      "lottie_url": "https://iconscout.com/lottie-animation/woman-doing-overhead-forward-lunges-exercise-for-legs-animation_12193227",
      "target_areas": [
        "quads",
        "glutes",
        "upperBody"
      ],
      "type": "strength",
      "impact": "low",
      "difficulty": 3,
      "met": 6.0,
      "symmetry": "alternating",
      "default_side": null,
      "default_duration_sec": 30,
      "rest_after_sec": 15,
      "note": "",
      "pace": "rep",
      "position": "standing",
      "lottie_file": "woman-doing-overhead-forward-lunges-exercise-for-legs"
    },
    {
      "id": "overhead_reverse_lunge",
      "name": "Overhead Reverse Lunge",
      "lottie_id": 12193236,
      "lottie_url": "https://iconscout.com/lottie-animation/woman-doing-overhead-reverse-lunges-exercise-for-legs-animation_12193236",
      "target_areas": [
        "quads",
        "glutes",
        "upperBody"
      ],
      "type": "strength",
      "impact": "low",
      "difficulty": 3,
      "met": 6.0,
      "symmetry": "alternating",
      "default_side": null,
      "default_duration_sec": 30,
      "rest_after_sec": 15,
      "note": "",
      "pace": "rep",
      "position": "standing",
      "lottie_file": "woman-doing-overhead-reverse-lunges-exercise-for-legs"
    },
    {
      "id": "side_lunge",
      "name": "Side Lunge",
      "lottie_id": 12193243,
      "lottie_url": "https://iconscout.com/lottie-animation/woman-doing-side-lunge-exercise-for-legs-animation_12193243",
      "target_areas": [
        "glutes",
        "quads"
      ],
      "type": "strength",
      "impact": "low",
      "difficulty": 2,
      "met": 5.5,
      "symmetry": "unilateral",
      "default_side": "left",
      "default_duration_sec": 30,
      "rest_after_sec": 15,
      "note": "Mirror animation horizontally to render the right side.",
      "pace": "rep",
      "position": "standing",
      "lottie_file": "woman-doing-side-lunge-exercise-for-legs"
    },
    {
      "id": "side_lying_hip_abduction",
      "name": "Side-Lying Hip Abduction",
      "lottie_id": 12193225,
      "lottie_url": "https://iconscout.com/lottie-animation/woman-doing-side-lying-hip-abduction-exercise-for-legs-animation_12193225",
      "target_areas": [
        "glutes"
      ],
      "type": "strength",
      "impact": "low",
      "difficulty": 1,
      "met": 3.5,
      "symmetry": "unilateral",
      "default_side": "left",
      "default_duration_sec": 30,
      "rest_after_sec": 15,
      "note": "Mirror animation horizontally to render the right side.",
      "pace": "rep",
      "position": "sideLying",
      "lottie_file": "woman-doing-side-lying-hip-abduction-exercise-for-legs"
    },
    {
      "id": "side_plank_hip_abduction",
      "name": "Side Plank Hip Abduction",
      "lottie_id": 12193224,
      "lottie_url": "https://iconscout.com/lottie-animation/woman-doing-side-plank-hip-abduction-exercise-for-legs-animation_12193224",
      "target_areas": [
        "obliques",
        "glutes"
      ],
      "type": "core",
      "impact": "low",
      "difficulty": 4,
      "met": 5.0,
      "symmetry": "unilateral",
      "default_side": "left",
      "default_duration_sec": 30,
      "rest_after_sec": 15,
      "note": "Mirror animation horizontally to render the right side.",
      "pace": "rep",
      "position": "sideLying",
      "lottie_file": "woman-doing-side-plank-hip-abduction-exercise-for-legs"
    },
    {
      "id": "side_split_squat",
      "name": "Side Split Squat",
      "lottie_id": 12193242,
      "lottie_url": "https://iconscout.com/lottie-animation/woman-doing-side-split-squat-exercise-for-legs-animation_12193242",
      "target_areas": [
        "quads",
        "glutes"
      ],
      "type": "strength",
      "impact": "low",
      "difficulty": 3,
      "met": 5.5,
      "symmetry": "unilateral",
      "default_side": "left",
      "default_duration_sec": 30,
      "rest_after_sec": 15,
      "note": "Mirror animation horizontally to render the right side.",
      "pace": "rep",
      "position": "standing",
      "lottie_file": "woman-doing-side-split-squat-exercise-for-legs"
    },
    {
      "id": "single_leg_glute_bridge",
      "name": "Single-Leg Glute Bridge",
      "lottie_id": 12193208,
      "lottie_url": "https://iconscout.com/lottie-animation/woman-doing-single-leg-glute-bridge-exercise-for-legs-animation_12193208",
      "target_areas": [
        "glutes"
      ],
      "type": "strength",
      "impact": "low",
      "difficulty": 2,
      "met": 4.5,
      "symmetry": "unilateral",
      "default_side": "left",
      "default_duration_sec": 30,
      "rest_after_sec": 15,
      "note": "Mirror animation horizontally to render the right side.",
      "pace": "rep",
      "position": "supine",
      "lottie_file": "woman-doing-single-leg-glute-bridge-exercise-for-legs"
    },
    {
      "id": "single_leg_rdl",
      "name": "Single-Leg RDL",
      "lottie_id": 12193223,
      "lottie_url": "https://iconscout.com/lottie-animation/woman-doing-single-leg-romanian-deadlift-exercise-for-legs-animation_12193223",
      "target_areas": [
        "hamstrings",
        "glutes"
      ],
      "type": "balance",
      "impact": "low",
      "difficulty": 4,
      "met": 5.0,
      "symmetry": "unilateral",
      "default_side": "left",
      "default_duration_sec": 30,
      "rest_after_sec": 15,
      "note": "Mirror animation horizontally to render the right side.",
      "pace": "rep",
      "position": "standing",
      "lottie_file": "woman-doing-single-leg-romanian-deadlift-exercise-for-legs"
    },
    {
      "id": "stiff_leg_deadlift",
      "name": "Stiff-Leg Deadlift",
      "lottie_id": 12193222,
      "lottie_url": "https://iconscout.com/lottie-animation/woman-doing-single-stiff-leg-deadlift-exercise-for-legs-animation_12193222",
      "target_areas": [
        "hamstrings",
        "glutes"
      ],
      "type": "balance",
      "impact": "low",
      "difficulty": 4,
      "met": 5.0,
      "symmetry": "unilateral",
      "default_side": "left",
      "default_duration_sec": 30,
      "rest_after_sec": 15,
      "note": "Mirror animation horizontally to render the right side.",
      "pace": "rep",
      "position": "standing",
      "lottie_file": "woman-doing-single-stiff-leg-deadlift-exercise-for-legs"
    },
    {
      "id": "split_squat",
      "name": "Split Squat",
      "lottie_id": 12193246,
      "lottie_url": "https://iconscout.com/lottie-animation/woman-doing-split-squat-exercise-for-legs-animation_12193246",
      "target_areas": [
        "quads",
        "glutes"
      ],
      "type": "strength",
      "impact": "low",
      "difficulty": 3,
      "met": 5.5,
      "symmetry": "unilateral",
      "default_side": "right",
      "default_duration_sec": 30,
      "rest_after_sec": 15,
      "note": "Mirror animation horizontally to render the left side.",
      "pace": "rep",
      "position": "standing",
      "lottie_file": "woman-doing-split-squat-exercise-for-legs"
    },
    {
      "id": "squat",
      "name": "Squat",
      "lottie_id": 12193255,
      "lottie_url": "https://iconscout.com/lottie-animation/woman-doing-squat-exercise-for-legs-animation_12193255",
      "target_areas": [
        "quads",
        "glutes"
      ],
      "type": "strength",
      "impact": "low",
      "difficulty": 2,
      "met": 5.5,
      "symmetry": "bilateral",
      "default_side": null,
      "default_duration_sec": 30,
      "rest_after_sec": 15,
      "note": "",
      "pace": "rep",
      "position": "standing",
      "lottie_file": "woman-doing-squat-exercise-for-legs"
    },
    {
      "id": "squat_calf_raise",
      "name": "Squat to Calf Raise",
      "lottie_id": 12193254,
      "lottie_url": "https://iconscout.com/lottie-animation/woman-doing-squat-to-calf-raise-exercise-for-legs-animation_12193254",
      "target_areas": [
        "quads",
        "glutes",
        "calves"
      ],
      "type": "strength",
      "impact": "low",
      "difficulty": 2,
      "met": 5.5,
      "symmetry": "bilateral",
      "default_side": null,
      "default_duration_sec": 30,
      "rest_after_sec": 15,
      "note": "",
      "pace": "rep",
      "position": "standing",
      "lottie_file": "woman-doing-squat-to-calf-raise-exercise-for-legs"
    },
    {
      "id": "pulse_squat",
      "name": "Pulse Squat",
      "lottie_id": 12193221,
      "lottie_url": "https://iconscout.com/lottie-animation/woman-doing-squat-with-pulse-exercise-for-legs-animation_12193221",
      "target_areas": [
        "quads",
        "glutes"
      ],
      "type": "strength",
      "impact": "low",
      "difficulty": 3,
      "met": 6.0,
      "symmetry": "bilateral",
      "default_side": null,
      "default_duration_sec": 30,
      "rest_after_sec": 15,
      "note": "",
      "pace": "rep",
      "position": "standing",
      "lottie_file": "woman-doing-squat-with-pulse-exercise-for-legs"
    },
    {
      "id": "calf_raise",
      "name": "Calf Raise",
      "lottie_id": 12193229,
      "lottie_url": "https://iconscout.com/lottie-animation/woman-doing-standing-calf-raise-exercise-for-legs-animation_12193229",
      "target_areas": [
        "calves"
      ],
      "type": "strength",
      "impact": "low",
      "difficulty": 1,
      "met": 3.0,
      "symmetry": "bilateral",
      "default_side": null,
      "default_duration_sec": 30,
      "rest_after_sec": 15,
      "note": "",
      "pace": "rep",
      "position": "standing",
      "lottie_file": "woman-doing-standing-calf-raise-exercise-for-legs"
    },
    {
      "id": "single_leg_calf_raise",
      "name": "Single-Leg Calf Raise",
      "lottie_id": 12193213,
      "lottie_url": "https://iconscout.com/lottie-animation/woman-doing-standing-single-leg-calf-raise-exercise-for-legs-animation_12193213",
      "target_areas": [
        "calves"
      ],
      "type": "balance",
      "impact": "low",
      "difficulty": 2,
      "met": 3.5,
      "symmetry": "unilateral",
      "default_side": "right",
      "default_duration_sec": 30,
      "rest_after_sec": 15,
      "note": "Mirror animation horizontally to render the left side.",
      "pace": "rep",
      "position": "standing",
      "lottie_file": "woman-doing-standing-single-leg-calf-raise-exercise-for-legs"
    },
    {
      "id": "sumo_squat",
      "name": "Sumo Squat",
      "lottie_id": 12193253,
      "lottie_url": "https://iconscout.com/lottie-animation/woman-doing-sumo-squat-exercise-for-legs-animation_12193253",
      "target_areas": [
        "quads",
        "glutes"
      ],
      "type": "strength",
      "impact": "low",
      "difficulty": 2,
      "met": 5.5,
      "symmetry": "bilateral",
      "default_side": null,
      "default_duration_sec": 30,
      "rest_after_sec": 15,
      "note": "",
      "pace": "rep",
      "position": "standing",
      "lottie_file": "woman-doing-sumo-squat-exercise-for-legs"
    },
    {
      "id": "wall_sit",
      "name": "Wall Sit",
      "lottie_id": 12193241,
      "lottie_url": "https://iconscout.com/lottie-animation/woman-doing-wall-sit-exercise-for-legs-animation_12193241",
      "target_areas": [
        "quads"
      ],
      "type": "core",
      "impact": "low",
      "difficulty": 3,
      "met": 5.0,
      "symmetry": "bilateral",
      "default_side": null,
      "default_duration_sec": 30,
      "rest_after_sec": 15,
      "note": "",
      "pace": "hold",
      "position": "standing",
      "lottie_file": "woman-doing-wall-sit-exercise-for-legs"
    },
    {
      "id": "skipping",
      "name": "Skipping",
      "lottie_id": 12349335,
      "lottie_url": "https://iconscout.com/lottie-animation/woman-doing-bodyweight-skipping-cardio-exercise-animation_12349335",
      "target_areas": [
        "calves",
        "fullBody"
      ],
      "type": "cardio",
      "impact": "med",
      "difficulty": 2,
      "met": 7.5,
      "symmetry": "bilateral",
      "default_side": null,
      "default_duration_sec": 30,
      "rest_after_sec": 15,
      "note": "",
      "pace": "rep",
      "position": "standing",
      "lottie_file": "woman-doing-bodyweight-skipping-cardio-exercise"
    },
    {
      "id": "bodyweight_swing",
      "name": "Bodyweight Swing",
      "lottie_id": 12349324,
      "lottie_url": "https://iconscout.com/lottie-animation/woman-doing-bodyweight-swing-cardio-exercise-animation_12349324",
      "target_areas": [
        "fullBody"
      ],
      "type": "cardio",
      "impact": "low",
      "difficulty": 2,
      "met": 6.0,
      "symmetry": "bilateral",
      "default_side": null,
      "default_duration_sec": 30,
      "rest_after_sec": 15,
      "note": "",
      "pace": "rep",
      "position": "standing",
      "lottie_file": "woman-doing-bodyweight-swing-cardio-exercise"
    },
    {
      "id": "burpee",
      "name": "Burpee",
      "lottie_id": 12349325,
      "lottie_url": "https://iconscout.com/lottie-animation/woman-doing-burpee-cardio-exercise-animation_12349325",
      "target_areas": [
        "fullBody"
      ],
      "type": "cardio",
      "impact": "high",
      "difficulty": 4,
      "met": 9.0,
      "symmetry": "bilateral",
      "default_side": null,
      "default_duration_sec": 30,
      "rest_after_sec": 15,
      "note": "",
      "pace": "rep",
      "position": "standing",
      "lottie_file": "woman-doing-burpee-cardio-exercise"
    },
    {
      "id": "burpee_no_jump",
      "name": "Burpee (No Jump)",
      "lottie_id": 12349326,
      "lottie_url": "https://iconscout.com/lottie-animation/woman-doing-burpee-no-jump-cardio-exercise-animation_12349326",
      "target_areas": [
        "fullBody"
      ],
      "type": "cardio",
      "impact": "med",
      "difficulty": 3,
      "met": 7.5,
      "symmetry": "bilateral",
      "default_side": null,
      "default_duration_sec": 30,
      "rest_after_sec": 15,
      "note": "",
      "pace": "rep",
      "position": "standing",
      "lottie_file": "woman-doing-burpee-no-jump-cardio-exercise"
    },
    {
      "id": "burpee_pushup",
      "name": "Burpee + Push-Up",
      "lottie_id": 12349327,
      "lottie_url": "https://iconscout.com/lottie-animation/woman-doing-burpee-with-push-up-cardio-exercise-animation_12349327",
      "target_areas": [
        "fullBody",
        "upperBody"
      ],
      "type": "cardio",
      "impact": "high",
      "difficulty": 5,
      "met": 10.0,
      "symmetry": "bilateral",
      "default_side": null,
      "default_duration_sec": 30,
      "rest_after_sec": 15,
      "note": "",
      "pace": "rep",
      "position": "standing",
      "lottie_file": "woman-doing-burpee-with-push-up-cardio-exercise"
    },
    {
      "id": "butt_kicks",
      "name": "Butt Kicks",
      "lottie_id": 12349313,
      "lottie_url": "https://iconscout.com/lottie-animation/woman-doing-butt-kicks-cardio-exercise-animation_12349313",
      "target_areas": [
        "hamstrings"
      ],
      "type": "cardio",
      "impact": "med",
      "difficulty": 2,
      "met": 7.0,
      "symmetry": "alternating",
      "default_side": null,
      "default_duration_sec": 30,
      "rest_after_sec": 15,
      "note": "",
      "pace": "rep",
      "position": "standing",
      "lottie_file": "woman-doing-butt-kicks-cardio-exercise"
    },
    {
      "id": "crab_toe_touches",
      "name": "Crab Toe Touches",
      "lottie_id": 12349314,
      "lottie_url": "https://iconscout.com/lottie-animation/woman-doing-crab-toe-touches-cardio-exercise-animation_12349314",
      "target_areas": [
        "abs",
        "upperBody"
      ],
      "type": "cardio",
      "impact": "low",
      "difficulty": 3,
      "met": 6.0,
      "symmetry": "alternating",
      "default_side": null,
      "default_duration_sec": 30,
      "rest_after_sec": 15,
      "note": "",
      "pace": "rep",
      "position": "seated",
      "lottie_file": "woman-doing-crab-toe-touches-cardio-exercise"
    },
    {
      "id": "front_kicks",
      "name": "Front Kicks",
      "lottie_id": 12349315,
      "lottie_url": "https://iconscout.com/lottie-animation/woman-doing-front-kicks-cardio-exercise-animation_12349315",
      "target_areas": [
        "quads",
        "abs"
      ],
      "type": "cardio",
      "impact": "med",
      "difficulty": 2,
      "met": 6.0,
      "symmetry": "alternating",
      "default_side": null,
      "default_duration_sec": 30,
      "rest_after_sec": 15,
      "note": "",
      "pace": "rep",
      "position": "standing",
      "lottie_file": "woman-doing-front-kicks-cardio-exercise"
    },
    {
      "id": "high_knees",
      "name": "High Knees",
      "lottie_id": 12349316,
      "lottie_url": "https://iconscout.com/lottie-animation/woman-doing-high-knee-taps-cardio-exercise-animation_12349316",
      "target_areas": [
        "quads",
        "abs"
      ],
      "type": "cardio",
      "impact": "med",
      "difficulty": 2,
      "met": 7.0,
      "symmetry": "alternating",
      "default_side": null,
      "default_duration_sec": 30,
      "rest_after_sec": 15,
      "note": "",
      "pace": "rep",
      "position": "standing",
      "lottie_file": "woman-doing-high-knee-taps-cardio-exercise"
    },
    {
      "id": "jumping_jacks",
      "name": "Jumping Jacks",
      "lottie_id": 12349337,
      "lottie_url": "https://iconscout.com/lottie-animation/woman-doing-jumping-jack-cardio-exercise-animation_12349337",
      "target_areas": [
        "fullBody"
      ],
      "type": "cardio",
      "impact": "high",
      "difficulty": 2,
      "met": 8.0,
      "symmetry": "bilateral",
      "default_side": null,
      "default_duration_sec": 30,
      "rest_after_sec": 15,
      "note": "",
      "pace": "rep",
      "position": "standing",
      "lottie_file": "woman-doing-jumping-jack-cardio-exercise"
    },
    {
      "id": "modified_burpee",
      "name": "Modified Burpee",
      "lottie_id": 12349328,
      "lottie_url": "https://iconscout.com/lottie-animation/woman-doing-modified-burpee-cardio-exercise-animation_12349328",
      "target_areas": [
        "fullBody"
      ],
      "type": "cardio",
      "impact": "low",
      "difficulty": 2,
      "met": 6.0,
      "symmetry": "bilateral",
      "default_side": null,
      "default_duration_sec": 30,
      "rest_after_sec": 15,
      "note": "",
      "pace": "rep",
      "position": "standing",
      "lottie_file": "woman-doing-modified-burpee-cardio-exercise"
    },
    {
      "id": "modified_jacks",
      "name": "Modified Jumping Jacks",
      "lottie_id": 12349338,
      "lottie_url": "https://iconscout.com/lottie-animation/woman-doing-modified-jumping-jack-cardio-exercise-animation_12349338",
      "target_areas": [
        "fullBody"
      ],
      "type": "cardio",
      "impact": "low",
      "difficulty": 1,
      "met": 5.0,
      "symmetry": "bilateral",
      "default_side": null,
      "default_duration_sec": 30,
      "rest_after_sec": 15,
      "note": "",
      "pace": "rep",
      "position": "standing",
      "lottie_file": "woman-doing-modified-jumping-jack-cardio-exercise"
    },
    {
      "id": "plank_frog_jump",
      "name": "Plank Frog Jump",
      "lottie_id": 12349329,
      "lottie_url": "https://iconscout.com/lottie-animation/woman-doing-plank-frog-jump-cardio-exercise-animation_12349329",
      "target_areas": [
        "abs",
        "fullBody"
      ],
      "type": "cardio",
      "impact": "med",
      "difficulty": 4,
      "met": 8.0,
      "symmetry": "bilateral",
      "default_side": null,
      "default_duration_sec": 30,
      "rest_after_sec": 15,
      "note": "",
      "pace": "rep",
      "position": "plank",
      "lottie_file": "woman-doing-plank-frog-jump-cardio-exercise"
    },
    {
      "id": "plank_jacks",
      "name": "Plank Jacks",
      "lottie_id": 12349317,
      "lottie_url": "https://iconscout.com/lottie-animation/woman-doing-plank-jack-cardio-exercise-animation_12349317",
      "target_areas": [
        "abs",
        "fullBody"
      ],
      "type": "cardio",
      "impact": "med",
      "difficulty": 3,
      "met": 7.0,
      "symmetry": "bilateral",
      "default_side": null,
      "default_duration_sec": 30,
      "rest_after_sec": 15,
      "note": "",
      "pace": "rep",
      "position": "plank",
      "lottie_file": "woman-doing-plank-jack-cardio-exercise"
    },
    {
      "id": "boxing_punches",
      "name": "Boxing Punches",
      "lottie_id": 12349320,
      "lottie_url": "https://iconscout.com/lottie-animation/woman-doing-punches-cardio-exercise-animation_12349320",
      "target_areas": [
        "upperBody"
      ],
      "type": "cardio",
      "impact": "low",
      "difficulty": 2,
      "met": 6.0,
      "symmetry": "alternating",
      "default_side": null,
      "default_duration_sec": 30,
      "rest_after_sec": 15,
      "note": "",
      "pace": "rep",
      "position": "standing",
      "lottie_file": "woman-doing-punches-cardio-exercise"
    },
    {
      "id": "run_punch",
      "name": "Run + Punch",
      "lottie_id": 12349318,
      "lottie_url": "https://iconscout.com/lottie-animation/woman-doing-running-in-place-and-punches-cardio-exercise-animation_12349318",
      "target_areas": [
        "fullBody"
      ],
      "type": "cardio",
      "impact": "med",
      "difficulty": 2,
      "met": 7.0,
      "symmetry": "alternating",
      "default_side": null,
      "default_duration_sec": 30,
      "rest_after_sec": 15,
      "note": "",
      "pace": "rep",
      "position": "standing",
      "lottie_file": "woman-doing-running-in-place-and-punches-cardio-exercise"
    },
    {
      "id": "run_in_place",
      "name": "Run in Place",
      "lottie_id": 12349319,
      "lottie_url": "https://iconscout.com/lottie-animation/woman-doing-running-in-place-cardio-exercise-animation_12349319",
      "target_areas": [
        "quads"
      ],
      "type": "cardio",
      "impact": "med",
      "difficulty": 2,
      "met": 7.0,
      "symmetry": "alternating",
      "default_side": null,
      "default_duration_sec": 30,
      "rest_after_sec": 15,
      "note": "",
      "pace": "rep",
      "position": "standing",
      "lottie_file": "woman-doing-running-in-place-cardio-exercise"
    },
    {
      "id": "plank_run",
      "name": "Plank Run",
      "lottie_id": 12349322,
      "lottie_url": "https://iconscout.com/lottie-animation/woman-doing-running-plank-cardio-exercise-animation_12349322",
      "target_areas": [
        "abs",
        "fullBody"
      ],
      "type": "cardio",
      "impact": "med",
      "difficulty": 3,
      "met": 7.5,
      "symmetry": "alternating",
      "default_side": null,
      "default_duration_sec": 30,
      "rest_after_sec": 15,
      "note": "",
      "pace": "rep",
      "position": "plank",
      "lottie_file": "woman-doing-running-plank-cardio-exercise"
    },
    {
      "id": "side_jacks",
      "name": "Side Jacks",
      "lottie_id": 12349332,
      "lottie_url": "https://iconscout.com/lottie-animation/woman-doing-side-jack-cardio-exercise-animation_12349332",
      "target_areas": [
        "fullBody"
      ],
      "type": "cardio",
      "impact": "med",
      "difficulty": 2,
      "met": 7.0,
      "symmetry": "alternating",
      "default_side": null,
      "default_duration_sec": 30,
      "rest_after_sec": 15,
      "note": "",
      "pace": "rep",
      "position": "standing",
      "lottie_file": "woman-doing-side-jack-cardio-exercise"
    },
    {
      "id": "side_leg_jack",
      "name": "Side Leg Jack",
      "lottie_id": 12349333,
      "lottie_url": "https://iconscout.com/lottie-animation/woman-doing-side-leg-raise-jack-cardio-exercise-animation_12349333",
      "target_areas": [
        "glutes"
      ],
      "type": "cardio",
      "impact": "med",
      "difficulty": 3,
      "met": 7.0,
      "symmetry": "alternating",
      "default_side": null,
      "default_duration_sec": 30,
      "rest_after_sec": 15,
      "note": "",
      "pace": "rep",
      "position": "standing",
      "lottie_file": "woman-doing-side-leg-raise-jack-cardio-exercise"
    },
    {
      "id": "simple_jacks",
      "name": "Simple Jumping Jacks",
      "lottie_id": 12349334,
      "lottie_url": "https://iconscout.com/lottie-animation/woman-doing-simplified-jumping-jack-cardio-exercise-animation_12349334",
      "target_areas": [
        "fullBody"
      ],
      "type": "cardio",
      "impact": "low",
      "difficulty": 1,
      "met": 5.0,
      "symmetry": "bilateral",
      "default_side": null,
      "default_duration_sec": 30,
      "rest_after_sec": 15,
      "note": "",
      "pace": "rep",
      "position": "standing",
      "lottie_file": "woman-doing-simplified-jumping-jack-cardio-exercise"
    },
    {
      "id": "jump_squat",
      "name": "Jump Squat",
      "lottie_id": 12349310,
      "lottie_url": "https://iconscout.com/lottie-animation/woman-doing-squat-jump-cardio-exercise-animation_12349310",
      "target_areas": [
        "quads",
        "glutes"
      ],
      "type": "cardio",
      "impact": "high",
      "difficulty": 4,
      "met": 8.5,
      "symmetry": "bilateral",
      "default_side": null,
      "default_duration_sec": 30,
      "rest_after_sec": 15,
      "note": "",
      "pace": "rep",
      "position": "standing",
      "lottie_file": "woman-doing-squat-jump-cardio-exercise"
    },
    {
      "id": "squat_front_kick",
      "name": "Squat + Front Kick",
      "lottie_id": 12349311,
      "lottie_url": "https://iconscout.com/lottie-animation/woman-doing-squat-with-front-kicks-cardio-exercise-animation_12349311",
      "target_areas": [
        "quads",
        "abs"
      ],
      "type": "cardio",
      "impact": "med",
      "difficulty": 3,
      "met": 7.0,
      "symmetry": "alternating",
      "default_side": null,
      "default_duration_sec": 30,
      "rest_after_sec": 15,
      "note": "",
      "pace": "rep",
      "position": "standing",
      "lottie_file": "woman-doing-squat-with-front-kicks-cardio-exercise"
    },
    {
      "id": "sumo_jump_squat",
      "name": "Sumo Jump Squat",
      "lottie_id": 12349312,
      "lottie_url": "https://iconscout.com/lottie-animation/woman-doing-sumo-squat-jump-cardio-exercise-animation_12349312",
      "target_areas": [
        "quads",
        "glutes"
      ],
      "type": "cardio",
      "impact": "high",
      "difficulty": 4,
      "met": 8.5,
      "symmetry": "bilateral",
      "default_side": null,
      "default_duration_sec": 30,
      "rest_after_sec": 15,
      "note": "",
      "pace": "rep",
      "position": "standing",
      "lottie_file": "woman-doing-sumo-squat-jump-cardio-exercise"
    },
    {
      "id": "baby_cobra",
      "name": "Baby Cobra",
      "lottie_id": 12682305,
      "lottie_url": "https://iconscout.com/lottie-animation/woman-doing-baby-cobra-pose-stretching-animation_12682305",
      "target_areas": [
        "lowerBack"
      ],
      "type": "mobility",
      "impact": "low",
      "difficulty": 1,
      "met": 2.3,
      "symmetry": "bilateral",
      "default_side": null,
      "default_duration_sec": 20,
      "rest_after_sec": 15,
      "note": "",
      "pace": "hold",
      "position": "prone",
      "lottie_file": "woman-doing-baby-cobra-pose-stretching"
    },
    {
      "id": "bow_pose",
      "name": "Bow Pose",
      "lottie_id": 12682302,
      "lottie_url": "https://iconscout.com/lottie-animation/woman-doing-bow-pose-stretching-animation_12682302",
      "target_areas": [
        "lowerBack",
        "fullBody"
      ],
      "type": "mobility",
      "impact": "low",
      "difficulty": 3,
      "met": 2.5,
      "symmetry": "bilateral",
      "default_side": null,
      "default_duration_sec": 20,
      "rest_after_sec": 15,
      "note": "",
      "pace": "hold",
      "position": "prone",
      "lottie_file": "woman-doing-bow-pose-stretching"
    },
    {
      "id": "cat_cow",
      "name": "Cat-Cow",
      "lottie_id": 12682301,
      "lottie_url": "https://iconscout.com/lottie-animation/woman-doing-cat-cow-stretching-animation_12682301",
      "target_areas": [
        "lowerBack",
        "abs"
      ],
      "type": "mobility",
      "impact": "low",
      "difficulty": 1,
      "met": 2.3,
      "symmetry": "alternating",
      "default_side": null,
      "default_duration_sec": 30,
      "rest_after_sec": 15,
      "note": "",
      "pace": "hold",
      "position": "quadruped",
      "lottie_file": "woman-doing-cat-cow-stretching"
    },
    {
      "id": "cat_stretch",
      "name": "Cat Stretch",
      "lottie_id": 12682300,
      "lottie_url": "https://iconscout.com/lottie-animation/woman-doing-cat-stretching-animation_12682300",
      "target_areas": [
        "lowerBack"
      ],
      "type": "mobility",
      "impact": "low",
      "difficulty": 1,
      "met": 2.3,
      "symmetry": "bilateral",
      "default_side": null,
      "default_duration_sec": 20,
      "rest_after_sec": 15,
      "note": "",
      "pace": "hold",
      "position": "quadruped",
      "lottie_file": "woman-doing-cat-stretching"
    },
    {
      "id": "childs_pose",
      "name": "Child's Pose",
      "lottie_id": 12682309,
      "lottie_url": "https://iconscout.com/lottie-animation/woman-doing-childs-pose-back-stretching-animation_12682309",
      "target_areas": [
        "lowerBack"
      ],
      "type": "mobility",
      "impact": "low",
      "difficulty": 1,
      "met": 2.3,
      "symmetry": "bilateral",
      "default_side": null,
      "default_duration_sec": 30,
      "rest_after_sec": 15,
      "note": "",
      "pace": "hold",
      "position": "quadruped",
      "lottie_file": "woman-doing-childs-pose-back-stretching"
    },
    {
      "id": "cobra",
      "name": "Cobra",
      "lottie_id": 12682308,
      "lottie_url": "https://iconscout.com/lottie-animation/woman-doing-cobra-pose-stretching-animation_12682308",
      "target_areas": [
        "lowerBack"
      ],
      "type": "mobility",
      "impact": "low",
      "difficulty": 1,
      "met": 2.5,
      "symmetry": "bilateral",
      "default_side": null,
      "default_duration_sec": 20,
      "rest_after_sec": 15,
      "note": "",
      "pace": "hold",
      "position": "prone",
      "lottie_file": "woman-doing-cobra-pose-stretching"
    },
    {
      "id": "cow_stretch",
      "name": "Cow Stretch",
      "lottie_id": 12682307,
      "lottie_url": "https://iconscout.com/lottie-animation/woman-doing-cow-stretching-animation_12682307",
      "target_areas": [
        "lowerBack"
      ],
      "type": "mobility",
      "impact": "low",
      "difficulty": 1,
      "met": 2.3,
      "symmetry": "bilateral",
      "default_side": null,
      "default_duration_sec": 20,
      "rest_after_sec": 15,
      "note": "",
      "pace": "hold",
      "position": "quadruped",
      "lottie_file": "woman-doing-cow-stretching"
    },
    {
      "id": "shoulder_stretch",
      "name": "Shoulder Stretch",
      "lottie_id": 12682290,
      "lottie_url": "https://iconscout.com/lottie-animation/woman-doing-deep-shoulders-stretching-animation_12682290",
      "target_areas": [
        "upperBody"
      ],
      "type": "mobility",
      "impact": "low",
      "difficulty": 1,
      "met": 2.3,
      "symmetry": "bilateral",
      "default_side": null,
      "default_duration_sec": 20,
      "rest_after_sec": 15,
      "note": "",
      "pace": "hold",
      "position": "standing",
      "lottie_file": "woman-doing-deep-shoulders-stretching"
    },
    {
      "id": "downward_dog",
      "name": "Downward Dog",
      "lottie_id": 12682292,
      "lottie_url": "https://iconscout.com/lottie-animation/woman-doing-downward-facing-dog-stretching-animation_12682292",
      "target_areas": [
        "fullBody",
        "upperBody"
      ],
      "type": "mobility",
      "impact": "low",
      "difficulty": 2,
      "met": 2.8,
      "symmetry": "bilateral",
      "default_side": null,
      "default_duration_sec": 30,
      "rest_after_sec": 15,
      "note": "",
      "pace": "hold",
      "position": "quadruped",
      "lottie_file": "woman-doing-downward-facing-dog-stretching"
    },
    {
      "id": "puppy_pose",
      "name": "Puppy Pose",
      "lottie_id": 12682293,
      "lottie_url": "https://iconscout.com/lottie-animation/woman-doing-extended-puppy-pose-stretching-animation_12682293",
      "target_areas": [
        "upperBody"
      ],
      "type": "mobility",
      "impact": "low",
      "difficulty": 1,
      "met": 2.3,
      "symmetry": "bilateral",
      "default_side": null,
      "default_duration_sec": 20,
      "rest_after_sec": 15,
      "note": "",
      "pace": "hold",
      "position": "quadruped",
      "lottie_file": "woman-doing-extended-puppy-pose-stretching"
    },
    {
      "id": "forward_fold_bind",
      "name": "Forward Fold + Bind",
      "lottie_id": 12682294,
      "lottie_url": "https://iconscout.com/lottie-animation/woman-doing-forward-bending-hands-behind-stretching-animation_12682294",
      "target_areas": [
        "hamstrings"
      ],
      "type": "mobility",
      "impact": "low",
      "difficulty": 2,
      "met": 2.5,
      "symmetry": "bilateral",
      "default_side": null,
      "default_duration_sec": 20,
      "rest_after_sec": 15,
      "note": "",
      "pace": "hold",
      "position": "standing",
      "lottie_file": "woman-doing-forward-bending-hands-behind-stretching"
    },
    {
      "id": "neck_stretch",
      "name": "Neck Stretch",
      "lottie_id": 12682284,
      "lottie_url": "https://iconscout.com/lottie-animation/woman-doing-neck-and-trapezius-stretching-animation_12682284",
      "target_areas": [
        "upperBody"
      ],
      "type": "mobility",
      "impact": "low",
      "difficulty": 1,
      "met": 2.3,
      "symmetry": "unilateral",
      "default_side": "right",
      "default_duration_sec": 20,
      "rest_after_sec": 15,
      "note": "Mirror animation horizontally to render the left side.",
      "pace": "hold",
      "position": "standing",
      "lottie_file": "woman-doing-neck-and-trapezius-stretching"
    },
    {
      "id": "sphinx",
      "name": "Sphinx",
      "lottie_id": 12682288,
      "lottie_url": "https://iconscout.com/lottie-animation/woman-doing-sphinx-pose-stretching-animation_12682288",
      "target_areas": [
        "lowerBack"
      ],
      "type": "mobility",
      "impact": "low",
      "difficulty": 1,
      "met": 2.3,
      "symmetry": "bilateral",
      "default_side": null,
      "default_duration_sec": 20,
      "rest_after_sec": 15,
      "note": "Excel notes only-left; sphinx is symmetric \u2014 bilateral.",
      "pace": "hold",
      "position": "prone",
      "lottie_file": "woman-doing-sphinx-pose-stretching"
    },
    {
      "id": "side_tilt",
      "name": "Side Tilt",
      "lottie_id": 12682289,
      "lottie_url": "https://iconscout.com/lottie-animation/woman-doing-side-tilt-stretching-animation_12682289",
      "target_areas": [
        "obliques"
      ],
      "type": "mobility",
      "impact": "low",
      "difficulty": 1,
      "met": 2.3,
      "symmetry": "alternating",
      "default_side": null,
      "default_duration_sec": 20,
      "rest_after_sec": 15,
      "note": "",
      "pace": "hold",
      "position": "standing",
      "lottie_file": "woman-doing-side-tilt-stretching"
    },
    {
      "id": "backbend",
      "name": "Backbend",
      "lottie_id": 12682287,
      "lottie_url": "https://iconscout.com/lottie-animation/woman-doing-spinal-extension-backward-bending-stretching-animation_12682287",
      "target_areas": [
        "lowerBack"
      ],
      "type": "mobility",
      "impact": "low",
      "difficulty": 2,
      "met": 2.5,
      "symmetry": "bilateral",
      "default_side": null,
      "default_duration_sec": 20,
      "rest_after_sec": 15,
      "note": "",
      "pace": "hold",
      "position": "standing",
      "lottie_file": "woman-doing-spinal-extension-backward-bending-stretching"
    },
    {
      "id": "upward_dog",
      "name": "Upward Dog",
      "lottie_id": 12682276,
      "lottie_url": "https://iconscout.com/lottie-animation/woman-doing-upward-facing-dog-stretching-animation_12682276",
      "target_areas": [
        "lowerBack"
      ],
      "type": "mobility",
      "impact": "low",
      "difficulty": 2,
      "met": 2.5,
      "symmetry": "bilateral",
      "default_side": null,
      "default_duration_sec": 20,
      "rest_after_sec": 15,
      "note": "",
      "pace": "hold",
      "position": "prone",
      "lottie_file": "woman-doing-upward-facing-dog-stretching"
    },
    {
      "id": "reverse_tabletop",
      "name": "Reverse Tabletop",
      "lottie_id": 12682306,
      "lottie_url": "https://iconscout.com/lottie-animation/woman-doing-upward-table-pose-stretching-animation_12682306",
      "target_areas": [
        "fullBody"
      ],
      "type": "mobility",
      "impact": "low",
      "difficulty": 3,
      "met": 3.0,
      "symmetry": "bilateral",
      "default_side": null,
      "default_duration_sec": 20,
      "rest_after_sec": 15,
      "note": "",
      "pace": "hold",
      "position": "supine",
      "lottie_file": "woman-doing-upward-table-pose-stretching"
    },
    {
      "id": "deep_hip_flexor",
      "name": "Deep Hip Flexor Stretch",
      "lottie_id": 12443462,
      "lottie_url": "https://iconscout.com/lottie-animation/woman-doing-advanced-hip-flexor-stretching-animation_12443462",
      "target_areas": [
        "hipFlexors"
      ],
      "type": "mobility",
      "impact": "low",
      "difficulty": 3,
      "met": 2.5,
      "symmetry": "unilateral",
      "default_side": "right",
      "default_duration_sec": 25,
      "rest_after_sec": 15,
      "note": "Mirror animation horizontally to render the left side.",
      "pace": "hold",
      "position": "quadruped",
      "lottie_file": "woman-doing-advanced-hip-flexor-stretching"
    },
    {
      "id": "hamstring_stretch_standing",
      "name": "Standing Hamstring Stretch",
      "lottie_id": 12443465,
      "lottie_url": "https://iconscout.com/lottie-animation/woman-doing-hamstring-stretching-animation_12443465",
      "target_areas": [
        "hamstrings"
      ],
      "type": "mobility",
      "impact": "low",
      "difficulty": 1,
      "met": 2.3,
      "symmetry": "unilateral",
      "default_side": "left",
      "default_duration_sec": 25,
      "rest_after_sec": 15,
      "note": "Mirror animation horizontally to render the right side.",
      "pace": "hold",
      "position": "standing",
      "lottie_file": "woman-doing-hamstring-stretching"
    },
    {
      "id": "hip_flexor_stretch",
      "name": "Hip Flexor Stretch",
      "lottie_id": 12443466,
      "lottie_url": "https://iconscout.com/lottie-animation/woman-doing-hip-flexor-stretching-animation_12443466",
      "target_areas": [
        "hipFlexors"
      ],
      "type": "mobility",
      "impact": "low",
      "difficulty": 2,
      "met": 2.3,
      "symmetry": "unilateral",
      "default_side": "left",
      "default_duration_sec": 25,
      "rest_after_sec": 15,
      "note": "Mirror animation horizontally to render the right side.",
      "pace": "hold",
      "position": "quadruped",
      "lottie_file": "woman-doing-hip-flexor-stretching"
    },
    {
      "id": "knees_to_chest",
      "name": "Knees to Chest",
      "lottie_id": 12443453,
      "lottie_url": "https://iconscout.com/lottie-animation/woman-doing-knees-to-chest-glute-stretching-animation_12443453",
      "target_areas": [
        "lowerBack",
        "glutes"
      ],
      "type": "mobility",
      "impact": "low",
      "difficulty": 1,
      "met": 2.3,
      "symmetry": "bilateral",
      "default_side": null,
      "default_duration_sec": 20,
      "rest_after_sec": 15,
      "note": "",
      "pace": "hold",
      "position": "supine",
      "lottie_file": "woman-doing-knees-to-chest-glute-stretching"
    },
    {
      "id": "lizard_pose",
      "name": "Lizard Pose",
      "lottie_id": 12443455,
      "lottie_url": "https://iconscout.com/lottie-animation/woman-doing-lizard-pose-stretching-animation_12443455",
      "target_areas": [
        "hipFlexors"
      ],
      "type": "mobility",
      "impact": "low",
      "difficulty": 3,
      "met": 2.5,
      "symmetry": "alternating",
      "default_side": null,
      "default_duration_sec": 20,
      "rest_after_sec": 15,
      "note": "",
      "pace": "hold",
      "position": "quadruped",
      "lottie_file": "woman-doing-lizard-pose-stretching"
    },
    {
      "id": "lying_glute_stretch",
      "name": "Lying Glute Stretch",
      "lottie_id": 12443457,
      "lottie_url": "https://iconscout.com/lottie-animation/woman-doing-lying-glute-stretching-animation_12443457",
      "target_areas": [
        "glutes"
      ],
      "type": "mobility",
      "impact": "low",
      "difficulty": 1,
      "met": 2.3,
      "symmetry": "unilateral",
      "default_side": "left",
      "default_duration_sec": 25,
      "rest_after_sec": 15,
      "note": "Mirror animation horizontally to render the right side.",
      "pace": "hold",
      "position": "supine",
      "lottie_file": "woman-doing-lying-glute-stretching"
    },
    {
      "id": "lying_hamstring_stretch",
      "name": "Lying Hamstring Stretch",
      "lottie_id": 12443458,
      "lottie_url": "https://iconscout.com/lottie-animation/woman-doing-lying-hamstring-stretching-animation_12443458",
      "target_areas": [
        "hamstrings"
      ],
      "type": "mobility",
      "impact": "low",
      "difficulty": 1,
      "met": 2.3,
      "symmetry": "unilateral",
      "default_side": "right",
      "default_duration_sec": 25,
      "rest_after_sec": 15,
      "note": "Mirror animation horizontally to render the left side.",
      "pace": "hold",
      "position": "supine",
      "lottie_file": "woman-doing-lying-hamstring-stretching"
    },
    {
      "id": "single_knee_to_chest",
      "name": "Single Knee to Chest",
      "lottie_id": 12443451,
      "lottie_url": "https://iconscout.com/lottie-animation/woman-doing-single-knee-to-chest-glute-stretching-animation_12443451",
      "target_areas": [
        "lowerBack",
        "glutes"
      ],
      "type": "mobility",
      "impact": "low",
      "difficulty": 1,
      "met": 2.3,
      "symmetry": "unilateral",
      "default_side": "right",
      "default_duration_sec": 25,
      "rest_after_sec": 15,
      "note": "Mirror animation horizontally to render the left side.",
      "pace": "hold",
      "position": "supine",
      "lottie_file": "woman-doing-single-knee-to-chest-glute-stretching"
    },
    {
      "id": "kneeling_quad_stretch",
      "name": "Kneeling Quad Stretch",
      "lottie_id": 12443447,
      "lottie_url": "https://iconscout.com/lottie-animation/woman-doing-sitting-kneeling-quadriceps-stretching-animation_12443447",
      "target_areas": [
        "quads"
      ],
      "type": "mobility",
      "impact": "low",
      "difficulty": 2,
      "met": 2.3,
      "symmetry": "alternating",
      "default_side": null,
      "default_duration_sec": 25,
      "rest_after_sec": 15,
      "note": "",
      "pace": "hold",
      "position": "seated",
      "lottie_file": "woman-doing-sitting-kneeling-quadriceps-stretching"
    },
    {
      "id": "seated_forward_fold",
      "name": "Seated Forward Fold",
      "lottie_id": 12443448,
      "lottie_url": "https://iconscout.com/lottie-animation/woman-doing-spinal-flexion-forward-bending-stretching-animation_12443448",
      "target_areas": [
        "lowerBack",
        "hamstrings"
      ],
      "type": "mobility",
      "impact": "low",
      "difficulty": 1,
      "met": 2.3,
      "symmetry": "bilateral",
      "default_side": null,
      "default_duration_sec": 25,
      "rest_after_sec": 15,
      "note": "",
      "pace": "hold",
      "position": "seated",
      "lottie_file": "woman-doing-spinal-flexion-forward-bending-stretching"
    },
    {
      "id": "standing_knee_hug",
      "name": "Standing Knee Hug",
      "lottie_id": 12443460,
      "lottie_url": "https://iconscout.com/lottie-animation/woman-doing-standing-knee-to-chest-glute-stretching-animation_12443460",
      "target_areas": [
        "lowerBack",
        "glutes"
      ],
      "type": "balance",
      "impact": "low",
      "difficulty": 2,
      "met": 2.5,
      "symmetry": "unilateral",
      "default_side": "right",
      "default_duration_sec": 20,
      "rest_after_sec": 15,
      "note": "Mirror animation horizontally to render the left side.",
      "pace": "hold",
      "position": "standing",
      "lottie_file": "woman-doing-standing-knee-to-chest-glute-stretching"
    },
    {
      "id": "standing_quad_stretch",
      "name": "Standing Quad Stretch",
      "lottie_id": 12443461,
      "lottie_url": "https://iconscout.com/lottie-animation/woman-doing-standing-quadricep-stretching-animation_12443461",
      "target_areas": [
        "quads"
      ],
      "type": "balance",
      "impact": "low",
      "difficulty": 2,
      "met": 2.5,
      "symmetry": "unilateral",
      "default_side": "right",
      "default_duration_sec": 20,
      "rest_after_sec": 15,
      "note": "Mirror animation horizontally to render the left side.",
      "pace": "hold",
      "position": "standing",
      "lottie_file": "woman-doing-standing-quadricep-stretching"
    }
  ]
}
